{"@context":"https://iiif.io/api/presentation/3/context.json","id":"https://mathewjordan.github.io/map-atlas-example/api/facet/date/1927.json","type":"Collection","label":{"none":["1927"]},"items":[{"id":"https://api.dc.library.northwestern.edu/api/v2/works/d33974ae-4cae-4c51-89be-9a39e7b22454?as=iiif","type":"Manifest","label":{"none":["Map of the Adirondack Forest and adjoining territory"]},"thumbnail":[{"id":"https://api.dc.library.northwestern.edu/api/v2/works/d33974ae-4cae-4c51-89be-9a39e7b22454/thumbnail","type":"Image","format":"image/jpeg","height":300,"width":300}],"homepage":[{"id":"https://mathewjordan.github.io/map-atlas-example/works/map-of-the-adirondack-forest-and-adjoining-territory","type":"Text","label":{"none":["Map of the Adirondack Forest and adjoining territory"]}}]},{"id":"https://api.dc.library.northwestern.edu/api/v2/works/ee7f90ad-14ea-4345-8c73-ca4e0e7ab18b?as=iiif","type":"Manifest","label":{"none":["Topographic map, Sequoia and General Grant National Parks, California"]},"thumbnail":[{"id":"https://api.dc.library.northwestern.edu/api/v2/works/ee7f90ad-14ea-4345-8c73-ca4e0e7ab18b/thumbnail","type":"Image","format":"image/jpeg","height":300,"width":300}],"homepage":[{"id":"https://mathewjordan.github.io/map-atlas-example/works/topographic-map-sequoia-and-general-grant-national-parks-california","type":"Text","label":{"none":["Topographic map, Sequoia and General Grant National Parks, California"]}}]}],"partOf":[{"id":"https://mathewjordan.github.io/map-atlas-example/api/facet/date.json","type":"Collection"}],"summary":{"none":["Date"]},"homepage":[{"id":"https://mathewjordan.github.io/map-atlas-example/search?date=1927","type":"Text","label":{"none":["1927"]}}]}