{"@context":"https://iiif.io/api/presentation/3/context.json","id":"https://mathewjordan.github.io/map-atlas-example/api/facet/date/1989.json","type":"Collection","label":{"none":["1989"]},"items":[{"id":"https://api.dc.library.northwestern.edu/api/v2/works/70d69241-c589-44db-87e7-469dbb9f1e84?as=iiif","type":"Manifest","label":{"none":["Gibraltar (U.K.)"]},"thumbnail":[{"id":"https://api.dc.library.northwestern.edu/api/v2/works/70d69241-c589-44db-87e7-469dbb9f1e84/thumbnail","type":"Image","format":"image/jpeg","height":300,"width":300}],"homepage":[{"id":"https://mathewjordan.github.io/map-atlas-example/works/gibraltar-uk","type":"Text","label":{"none":["Gibraltar (U.K.)"]}}]}],"partOf":[{"id":"https://mathewjordan.github.io/map-atlas-example/api/facet/date.json","type":"Collection"}],"summary":{"none":["Date"]},"homepage":[{"id":"https://mathewjordan.github.io/map-atlas-example/search?date=1989","type":"Text","label":{"none":["1989"]}}]}